{
  "date": "2026-05-08",
  "updated": "2026-05-08T13:25:11.762129+08:00",
  "source": "taifex_futContractsDate+taifex_futContractsDateAh+taifex_futDataDown+taifex_open_data+twse_bfi82u",
  "market": {
    "TX": {
      "symbol": "TX",
      "date": "2026-05-07",
      "front_month": "202605",
      "close": 42340.0,
      "settlement": 42352.0,
      "volume": 59558,
      "open_interest": 86565,
      "source": "taifex_open_data",
      "open_interest_total": 92713
    },
    "TMF": {
      "symbol": "TMF",
      "date": "2026-05-07",
      "front_month": "202605",
      "close": 42335.0,
      "settlement": 42352.0,
      "volume": 142995,
      "open_interest": 39347,
      "source": "taifex_open_data",
      "open_interest_total": 56181
    },
    "MTX": {
      "symbol": "MTX",
      "date": "2026-05-07",
      "front_month": "202605W2",
      "close": 42133.0,
      "settlement": 42133.0,
      "volume": 97,
      "open_interest": 71,
      "source": "taifex_open_data",
      "open_interest_total": 38654
    }
  },
  "stock_institutional": {
    "date": "2026-05-07",
    "history": [
      {
        "date": "2026-05-07",
        "traders": {
          "foreign": {
            "label": "外資",
            "buy_amount": 481490560104,
            "sell_amount": 435079033534,
            "net_amount": 46411526570
          },
          "investment_trust": {
            "label": "投信",
            "buy_amount": 34125520860,
            "sell_amount": 19073192148,
            "net_amount": 15052328712
          },
          "dealer": {
            "label": "自營商",
            "buy_amount": 44556611432,
            "sell_amount": 48698877879,
            "net_amount": -4142266447
          },
          "total": {
            "label": "三大法人合計",
            "buy_amount": 560172692396,
            "sell_amount": 502851103561,
            "net_amount": 57321588835
          }
        },
        "source": "twse_bfi82u",
        "unit": "TWD"
      },
      {
        "date": "2026-05-06",
        "traders": {
          "foreign": {
            "label": "外資",
            "buy_amount": 604269420170,
            "sell_amount": 529164512376,
            "net_amount": 75104907794
          },
          "investment_trust": {
            "label": "投信",
            "buy_amount": 33542780925,
            "sell_amount": 32021549000,
            "net_amount": 1521231925
          },
          "dealer": {
            "label": "自營商",
            "buy_amount": 65944682343,
            "sell_amount": 75555292975,
            "net_amount": -9610610632
          },
          "total": {
            "label": "三大法人合計",
            "buy_amount": 703756883438,
            "sell_amount": 636741354351,
            "net_amount": 67015529087
          }
        },
        "source": "twse_bfi82u",
        "unit": "TWD"
      },
      {
        "date": "2026-05-05",
        "traders": {
          "foreign": {
            "label": "外資",
            "buy_amount": 358109943345,
            "sell_amount": 354119676212,
            "net_amount": 3990267133
          },
          "investment_trust": {
            "label": "投信",
            "buy_amount": 26841381710,
            "sell_amount": 23114456726,
            "net_amount": 3726924984
          },
          "dealer": {
            "label": "自營商",
            "buy_amount": 38588422748,
            "sell_amount": 48675666564,
            "net_amount": -10087243816
          },
          "total": {
            "label": "三大法人合計",
            "buy_amount": 423539747803,
            "sell_amount": 425909799502,
            "net_amount": -2370051699
          }
        },
        "source": "twse_bfi82u",
        "unit": "TWD"
      },
      {
        "date": "2026-05-04",
        "traders": {
          "foreign": {
            "label": "外資",
            "buy_amount": 402015475312,
            "sell_amount": 335039774559,
            "net_amount": 66975700753
          },
          "investment_trust": {
            "label": "投信",
            "buy_amount": 16194865482,
            "sell_amount": 14166407936,
            "net_amount": 2028457546
          },
          "dealer": {
            "label": "自營商",
            "buy_amount": 48561133325,
            "sell_amount": 39620532189,
            "net_amount": 8940601136
          },
          "total": {
            "label": "三大法人合計",
            "buy_amount": 466771474119,
            "sell_amount": 388826714684,
            "net_amount": 77944759435
          }
        },
        "source": "twse_bfi82u",
        "unit": "TWD"
      },
      {
        "date": "2026-04-30",
        "traders": {
          "foreign": {
            "label": "外資",
            "buy_amount": 406259095898,
            "sell_amount": 459820821006,
            "net_amount": -53561725108
          },
          "investment_trust": {
            "label": "投信",
            "buy_amount": 14855053761,
            "sell_amount": 13771840985,
            "net_amount": 1083212776
          },
          "dealer": {
            "label": "自營商",
            "buy_amount": 39999615117,
            "sell_amount": 40788484701,
            "net_amount": -788869584
          },
          "total": {
            "label": "三大法人合計",
            "buy_amount": 461113764776,
            "sell_amount": 514381146692,
            "net_amount": -53267381916
          }
        },
        "source": "twse_bfi82u",
        "unit": "TWD"
      }
    ],
    "source": "twse_bfi82u",
    "unit": "TWD"
  },
  "futures": {
    "day_session": {
      "tx": {
        "date": "2026-05-07",
        "product": "臺股期貨",
        "traders": {
          "dealer": {
            "label": "自營商",
            "buy_lots": 6583,
            "sell_lots": 6389,
            "net_lots": 194,
            "oi_long_lots": 4645,
            "oi_short_lots": 5679,
            "oi_net_lots": -1034
          },
          "investment_trust": {
            "label": "投信",
            "buy_lots": 1433,
            "sell_lots": 354,
            "net_lots": 1079,
            "oi_long_lots": 50998,
            "oi_short_lots": 4821,
            "oi_net_lots": 46177
          },
          "foreign": {
            "label": "外資",
            "buy_lots": 64604,
            "sell_lots": 64767,
            "net_lots": -163,
            "oi_long_lots": 20333,
            "oi_short_lots": 71465,
            "oi_net_lots": -51132
          },
          "total": {
            "label": "三大法人合計",
            "buy_lots": 72620,
            "sell_lots": 71510,
            "net_lots": 1110,
            "oi_long_lots": 75976,
            "oi_short_lots": 81965,
            "oi_net_lots": -5989
          }
        },
        "source": "taifex_futContractsDate"
      },
      "mtx": {
        "date": "2026-05-07",
        "product": "小型臺指期貨",
        "traders": {
          "dealer": {
            "label": "自營商",
            "buy_lots": 13985,
            "sell_lots": 14071,
            "net_lots": -86,
            "oi_long_lots": 2894,
            "oi_short_lots": 7408,
            "oi_net_lots": -4514
          },
          "investment_trust": {
            "label": "投信",
            "buy_lots": 0,
            "sell_lots": 2,
            "net_lots": -2,
            "oi_long_lots": 113,
            "oi_short_lots": 40,
            "oi_net_lots": 73
          },
          "foreign": {
            "label": "外資",
            "buy_lots": 135408,
            "sell_lots": 135478,
            "net_lots": -70,
            "oi_long_lots": 4457,
            "oi_short_lots": 4399,
            "oi_net_lots": 58
          },
          "total": {
            "label": "三大法人合計",
            "buy_lots": 149393,
            "sell_lots": 149551,
            "net_lots": -158,
            "oi_long_lots": 7464,
            "oi_short_lots": 11847,
            "oi_net_lots": -4383
          }
        },
        "source": "taifex_futContractsDate"
      },
      "tmf": {
        "date": "2026-05-07",
        "product": "微型臺指期貨",
        "traders": {
          "dealer": {
            "label": "自營商",
            "buy_lots": 24520,
            "sell_lots": 23790,
            "net_lots": 730,
            "oi_long_lots": 2169,
            "oi_short_lots": 8317,
            "oi_net_lots": -6148
          },
          "investment_trust": {
            "label": "投信",
            "buy_lots": 0,
            "sell_lots": 0,
            "net_lots": 0,
            "oi_long_lots": 0,
            "oi_short_lots": 0,
            "oi_net_lots": 0
          },
          "foreign": {
            "label": "外資",
            "buy_lots": 148224,
            "sell_lots": 146045,
            "net_lots": 2179,
            "oi_long_lots": 4385,
            "oi_short_lots": 1096,
            "oi_net_lots": 3289
          },
          "total": {
            "label": "三大法人合計",
            "buy_lots": 172744,
            "sell_lots": 169835,
            "net_lots": 2909,
            "oi_long_lots": 6554,
            "oi_short_lots": 9413,
            "oi_net_lots": -2859
          }
        },
        "source": "taifex_futContractsDate"
      }
    },
    "night_session": {
      "tx": {
        "date": "2026-05-08",
        "product": "臺股期貨",
        "traders": {
          "dealer": {
            "label": "自營商",
            "buy_lots": 2127,
            "sell_lots": 1295,
            "net_lots": 832
          },
          "investment_trust": {
            "label": "投信",
            "buy_lots": 0,
            "sell_lots": 0,
            "net_lots": 0
          },
          "foreign": {
            "label": "外資",
            "buy_lots": 29390,
            "sell_lots": 31529,
            "net_lots": -2139
          },
          "total": {
            "label": "三大法人合計",
            "buy_lots": 31517,
            "sell_lots": 32824,
            "net_lots": -1307,
            "oi_long_lots": null,
            "oi_short_lots": null,
            "oi_net_lots": null
          }
        },
        "source": "taifex_futContractsDateAh"
      },
      "mtx": {
        "date": "2026-05-08",
        "product": "小型臺指期貨",
        "traders": {
          "dealer": {
            "label": "自營商",
            "buy_lots": 6405,
            "sell_lots": 6375,
            "net_lots": 30
          },
          "investment_trust": {
            "label": "投信",
            "buy_lots": 0,
            "sell_lots": 0,
            "net_lots": 0
          },
          "foreign": {
            "label": "外資",
            "buy_lots": 74863,
            "sell_lots": 78734,
            "net_lots": -3871
          },
          "total": {
            "label": "三大法人合計",
            "buy_lots": 81268,
            "sell_lots": 85109,
            "net_lots": -3841,
            "oi_long_lots": null,
            "oi_short_lots": null,
            "oi_net_lots": null
          }
        },
        "source": "taifex_futContractsDateAh"
      },
      "tmf": {
        "date": "2026-05-08",
        "product": "微型臺指期貨",
        "traders": {
          "dealer": {
            "label": "自營商",
            "buy_lots": 5290,
            "sell_lots": 17326,
            "net_lots": -12036
          },
          "investment_trust": {
            "label": "投信",
            "buy_lots": 0,
            "sell_lots": 0,
            "net_lots": 0
          },
          "foreign": {
            "label": "外資",
            "buy_lots": 87230,
            "sell_lots": 91229,
            "net_lots": -3999
          },
          "total": {
            "label": "三大法人合計",
            "buy_lots": 92520,
            "sell_lots": 108555,
            "net_lots": -16035,
            "oi_long_lots": null,
            "oi_short_lots": null,
            "oi_net_lots": null
          }
        },
        "source": "taifex_futContractsDateAh"
      }
    }
  },
  "sentiment": {
    "retail_long_short": {
      "date": "2026-05-07",
      "symbol": "MTX",
      "contract": "小型臺指期貨",
      "institutional_net_open_interest": -4383,
      "estimated_retail_net_open_interest": 4383,
      "market_open_interest": 38654,
      "ratio": 11.34,
      "definition": "三大法人淨未平倉反向值 / 全市場全月份未沖銷契約數；正值代表散戶相對偏多。",
      "source": "taifex_derived"
    },
    "retail_dashboard": {
      "date": "2026-05-07",
      "rows": [
        {
          "key": "mtx",
          "label": "小台散戶多空比",
          "format": "percent",
          "today": 11.34,
          "previous": 11.83,
          "change": -0.49,
          "trend": "下降",
          "date": "2026-05-07",
          "previous_date": "2026-05-06",
          "detail": {
            "date": "2026-05-07",
            "symbol": "MTX",
            "contract": "小型臺指期貨",
            "institutional_net_open_interest": -4383,
            "estimated_retail_net_open_interest": 4383,
            "market_open_interest": 38654,
            "ratio": 11.34,
            "definition": "三大法人淨未平倉反向值 / 全市場全月份未沖銷契約數；正值代表散戶相對偏多。",
            "source": "taifex_derived"
          },
          "history": [
            {
              "date": "2026-05-07",
              "symbol": "MTX",
              "contract": "小型臺指期貨",
              "institutional_net_open_interest": -4383,
              "estimated_retail_net_open_interest": 4383,
              "market_open_interest": 38654,
              "ratio": 11.34,
              "definition": "三大法人淨未平倉反向值 / 全市場全月份未沖銷契約數；正值代表散戶相對偏多。",
              "source": "taifex_derived"
            },
            {
              "date": "2026-05-06",
              "symbol": "MTX",
              "contract": "小型臺指期貨",
              "institutional_net_open_interest": -4326,
              "estimated_retail_net_open_interest": 4326,
              "market_open_interest": 36579,
              "ratio": 11.83,
              "definition": "三大法人淨未平倉反向值 / 全市場全月份未沖銷契約數；正值代表散戶相對偏多。",
              "source": "taifex_derived"
            },
            {
              "date": "2026-05-05",
              "symbol": "MTX",
              "contract": "小型臺指期貨",
              "institutional_net_open_interest": -1431,
              "estimated_retail_net_open_interest": 1431,
              "market_open_interest": 36120,
              "ratio": 3.96,
              "definition": "三大法人淨未平倉反向值 / 全市場全月份未沖銷契約數；正值代表散戶相對偏多。",
              "source": "taifex_derived"
            },
            {
              "date": "2026-05-04",
              "symbol": "MTX",
              "contract": "小型臺指期貨",
              "institutional_net_open_interest": 2236,
              "estimated_retail_net_open_interest": -2236,
              "market_open_interest": 37091,
              "ratio": -6.03,
              "definition": "三大法人淨未平倉反向值 / 全市場全月份未沖銷契約數；正值代表散戶相對偏多。",
              "source": "taifex_derived"
            },
            {
              "date": "2026-04-30",
              "symbol": "MTX",
              "contract": "小型臺指期貨",
              "institutional_net_open_interest": 1688,
              "estimated_retail_net_open_interest": -1688,
              "market_open_interest": 35716,
              "ratio": -4.73,
              "definition": "三大法人淨未平倉反向值 / 全市場全月份未沖銷契約數；正值代表散戶相對偏多。",
              "source": "taifex_derived"
            }
          ]
        },
        {
          "key": "tmf",
          "label": "微台散戶多空比",
          "format": "percent",
          "today": 5.09,
          "previous": 9.36,
          "change": -4.27,
          "trend": "下降",
          "date": "2026-05-07",
          "previous_date": "2026-05-06",
          "detail": {
            "date": "2026-05-07",
            "symbol": "TMF",
            "contract": "微型臺指期貨",
            "institutional_net_open_interest": -2859,
            "estimated_retail_net_open_interest": 2859,
            "market_open_interest": 56181,
            "ratio": 5.09,
            "definition": "三大法人淨未平倉反向值 / 全市場全月份未沖銷契約數；正值代表散戶相對偏多。",
            "source": "taifex_derived"
          },
          "history": [
            {
              "date": "2026-05-07",
              "symbol": "TMF",
              "contract": "微型臺指期貨",
              "institutional_net_open_interest": -2859,
              "estimated_retail_net_open_interest": 2859,
              "market_open_interest": 56181,
              "ratio": 5.09,
              "definition": "三大法人淨未平倉反向值 / 全市場全月份未沖銷契約數；正值代表散戶相對偏多。",
              "source": "taifex_derived"
            },
            {
              "date": "2026-05-06",
              "symbol": "TMF",
              "contract": "微型臺指期貨",
              "institutional_net_open_interest": -5123,
              "estimated_retail_net_open_interest": 5123,
              "market_open_interest": 54751,
              "ratio": 9.36,
              "definition": "三大法人淨未平倉反向值 / 全市場全月份未沖銷契約數；正值代表散戶相對偏多。",
              "source": "taifex_derived"
            },
            {
              "date": "2026-05-05",
              "symbol": "TMF",
              "contract": "微型臺指期貨",
              "institutional_net_open_interest": 1443,
              "estimated_retail_net_open_interest": -1443,
              "market_open_interest": 56102,
              "ratio": -2.57,
              "definition": "三大法人淨未平倉反向值 / 全市場全月份未沖銷契約數；正值代表散戶相對偏多。",
              "source": "taifex_derived"
            },
            {
              "date": "2026-05-04",
              "symbol": "TMF",
              "contract": "微型臺指期貨",
              "institutional_net_open_interest": 19070,
              "estimated_retail_net_open_interest": -19070,
              "market_open_interest": 65499,
              "ratio": -29.11,
              "definition": "三大法人淨未平倉反向值 / 全市場全月份未沖銷契約數；正值代表散戶相對偏多。",
              "source": "taifex_derived"
            },
            {
              "date": "2026-04-30",
              "symbol": "TMF",
              "contract": "微型臺指期貨",
              "institutional_net_open_interest": -4687,
              "estimated_retail_net_open_interest": 4687,
              "market_open_interest": 50760,
              "ratio": 9.23,
              "definition": "三大法人淨未平倉反向值 / 全市場全月份未沖銷契約數；正值代表散戶相對偏多。",
              "source": "taifex_derived"
            }
          ]
        },
        {
          "key": "pc_ratio",
          "label": "Put/Call Ratio",
          "format": "decimal",
          "today": 1.74,
          "previous": 1.78,
          "change": -0.04,
          "trend": "下降",
          "date": "2026-05-07",
          "previous_date": "2026-05-06",
          "detail": {
            "date": "2026-05-07",
            "put_volume": 202333,
            "call_volume": 157511,
            "volume_ratio": 128.46,
            "put_open_interest": 118801,
            "call_open_interest": 68224,
            "open_interest_ratio": 174.13,
            "ratio": 1.74,
            "source": "taifex_open_data"
          },
          "history": [
            {
              "date": "2026-05-07",
              "put_volume": 202333,
              "call_volume": 157511,
              "volume_ratio": 128.46,
              "put_open_interest": 118801,
              "call_open_interest": 68224,
              "open_interest_ratio": 174.13,
              "ratio": 1.74,
              "source": "taifex_open_data"
            },
            {
              "date": "2026-05-06",
              "put_volume": 500528,
              "call_volume": 443548,
              "volume_ratio": 112.85,
              "put_open_interest": 83697,
              "call_open_interest": 47129,
              "open_interest_ratio": 177.59,
              "ratio": 1.78,
              "source": "taifex_open_data"
            },
            {
              "date": "2026-05-05",
              "put_volume": 168069,
              "call_volume": 140074,
              "volume_ratio": 119.99,
              "put_open_interest": 118434,
              "call_open_interest": 76587,
              "open_interest_ratio": 154.64,
              "ratio": 1.55,
              "source": "taifex_open_data"
            },
            {
              "date": "2026-05-04",
              "put_volume": 346275,
              "call_volume": 267010,
              "volume_ratio": 129.69,
              "put_open_interest": 90034,
              "call_open_interest": 52989,
              "open_interest_ratio": 169.91,
              "ratio": 1.7,
              "source": "taifex_open_data"
            },
            {
              "date": "2026-04-30",
              "put_volume": 135799,
              "call_volume": 123293,
              "volume_ratio": 110.14,
              "put_open_interest": 107556,
              "call_open_interest": 67661,
              "open_interest_ratio": 158.96,
              "ratio": 1.59,
              "source": "taifex_open_data"
            }
          ]
        }
      ],
      "source": "taifex_futContractsDate+taifex_futDataDown+taifex_open_data",
      "definition": "散戶多空比採國泰報告呈現邏輯：三大法人未平倉淨額反向值除以同商品全市場未沖銷契約數，並列今日、前一日與增減方向。"
    },
    "pc_ratio": {
      "date": "2026-05-07",
      "put_volume": 202333,
      "call_volume": 157511,
      "volume_ratio": 128.46,
      "put_open_interest": 118801,
      "call_open_interest": 68224,
      "open_interest_ratio": 174.13,
      "ratio": 1.74,
      "source": "taifex_open_data",
      "history": [
        {
          "date": "2026-05-07",
          "put_volume": 202333,
          "call_volume": 157511,
          "volume_ratio": 128.46,
          "put_open_interest": 118801,
          "call_open_interest": 68224,
          "open_interest_ratio": 174.13,
          "ratio": 1.74,
          "source": "taifex_open_data"
        },
        {
          "date": "2026-05-06",
          "put_volume": 500528,
          "call_volume": 443548,
          "volume_ratio": 112.85,
          "put_open_interest": 83697,
          "call_open_interest": 47129,
          "open_interest_ratio": 177.59,
          "ratio": 1.78,
          "source": "taifex_open_data"
        },
        {
          "date": "2026-05-05",
          "put_volume": 168069,
          "call_volume": 140074,
          "volume_ratio": 119.99,
          "put_open_interest": 118434,
          "call_open_interest": 76587,
          "open_interest_ratio": 154.64,
          "ratio": 1.55,
          "source": "taifex_open_data"
        },
        {
          "date": "2026-05-04",
          "put_volume": 346275,
          "call_volume": 267010,
          "volume_ratio": 129.69,
          "put_open_interest": 90034,
          "call_open_interest": 52989,
          "open_interest_ratio": 169.91,
          "ratio": 1.7,
          "source": "taifex_open_data"
        },
        {
          "date": "2026-04-30",
          "put_volume": 135799,
          "call_volume": 123293,
          "volume_ratio": 110.14,
          "put_open_interest": 107556,
          "call_open_interest": 67661,
          "open_interest_ratio": 158.96,
          "ratio": 1.59,
          "source": "taifex_open_data"
        }
      ],
      "previous_ratio": 1.78,
      "change": -0.04,
      "trend": "下降"
    }
  },
  "summary": {
    "bias": "中性",
    "notes": [
      "夜盤法人為期交所三大法人夜盤頁面資料，日期以盤後交易量歸屬日為準。",
      "散戶多空比以三大法人淨未平倉反向值 / 全市場全月份未沖銷契約數估算；正值代表散戶相對偏多。"
    ]
  }
}
